please_do/__init__.py
please_do/__main__.py
please_do/main.py
please_do-0.1.0.dist-info/entry_points.txt
please_do-0.1.0.dist-info/METADATA
please_do-0.1.0.dist-info/WHEEL
please_do-0.1.0.dist-info/RECORD
