Metadata-Version: 2.1
Name: please-do
Version: 0.1.0
Summary: A Small CLI tool for running custom cli commands with shortcuts. Pythonic version of npm scripts
License: MIT
Author: Abror Aliboyev
Author-email: contact@aliboyev.com
Requires-Python: >=3.8,<4.0
Classifier: License :: OSI Approved :: MIT License
Classifier: Operating System :: OS Independent
Classifier: Programming Language :: Python :: 3
Classifier: Programming Language :: Python :: 3.8
Classifier: Programming Language :: Python :: 3.9
Classifier: Programming Language :: Python :: 3.10
Classifier: Programming Language :: Python :: 3.11
Requires-Dist: pyyaml (>=6.0.1,<7.0.0)
Requires-Dist: rich (>=13.7.1,<14.0.0)
Requires-Dist: typer[all] (>=0.12.0,<0.13.0)
Project-URL: Documentation, https://github.com/aaliboyev/please-do
Project-URL: Source, https://github.com/aaliboyev/please-do
